ftmstore/__init__.py
ftmstore/cli.py
ftmstore/dataset.py
ftmstore/loader.py
ftmstore/settings.py
ftmstore/store.py
ftmstore/utils.py
followthemoney_store-3.1.0.dist-info/LICENSE
followthemoney_store-3.1.0.dist-info/METADATA
followthemoney_store-3.1.0.dist-info/WHEEL
followthemoney_store-3.1.0.dist-info/entry_points.txt
followthemoney_store-3.1.0.dist-info/top_level.txt
followthemoney_store-3.1.0.dist-info/zip-safe
followthemoney_store-3.1.0.dist-info/RECORD
