Metadata-Version: 2.1
Name: followthemoney-store
Version: 3.1.0
Summary: Store raw and structured FollowTheMoney data from different datasets in a data lake
Home-page: http://github.com/alephdata/followthemoney-store
Author: Organized Crime and Corruption Reporting Project
Author-email: data@occrp.org
License: MIT
Platform: UNKNOWN
Classifier: Development Status :: 3 - Alpha
Classifier: Intended Audience :: Developers
Classifier: License :: OSI Approved :: MIT License
Classifier: Operating System :: OS Independent
Classifier: Programming Language :: Python :: 3.6
Classifier: Programming Language :: Python :: 3.7
Classifier: Programming Language :: Python :: 3.8
License-File: LICENSE
Provides-Extra: postgresql
Requires-Dist: psycopg2-binary (>=2.7) ; extra == 'postgresql'
